insta_share/__init__.py
insta_share/instagram.py
insta_share/utils.py
insta_share-0.0.1.dist-info/LICENSE
insta_share-0.0.1.dist-info/METADATA
insta_share-0.0.1.dist-info/WHEEL
insta_share-0.0.1.dist-info/top_level.txt
insta_share-0.0.1.dist-info/RECORD
