Metadata-Version: 2.1
Name: insta-share
Version: 0.0.1
Summary: Python package for sharing on Instagram
Home-page: https://github.com/softcoder24/insta_share
Author: soft_coder
License: apache-2.0
Platform: UNKNOWN
Classifier: Development Status :: 3 - Alpha
Classifier: Intended Audience :: Developers
Classifier: Topic :: Software Development
Classifier: License :: OSI Approved :: Apache Software License
Classifier: Programming Language :: Python :: 3
Requires-Python: >=3.6
